rest_batteries/__init__.py
rest_batteries/errors_formatter.py
rest_batteries/exception_handlers.py
rest_batteries/generics.py
rest_batteries/mixins.py
rest_batteries/views.py
rest_batteries/viewsets.py
django_rest_batteries-1.4.1.dist-info/LICENSE
django_rest_batteries-1.4.1.dist-info/WHEEL
django_rest_batteries-1.4.1.dist-info/METADATA
django_rest_batteries-1.4.1.dist-info/RECORD
