Metadata-Version: 2.1
Name: django-rest-batteries
Version: 1.4.1
Summary: Build clean APIs with DRF faster
Home-page: https://github.com/defineimpossible/django-rest-batteries
License: MIT
Keywords: django rest framework,drf,django,batteries
Author: Define Impossible
Author-email: hi@defineimpossible.io
Requires-Python: >=3.8,<4.0
Classifier: License :: OSI Approved :: MIT License
Classifier: Programming Language :: Python :: 3
Classifier: Programming Language :: Python :: 3.8
Classifier: Programming Language :: Python :: 3.9
Classifier: Programming Language :: Python :: 3.10
Classifier: Programming Language :: Python :: 3.11
Requires-Dist: django (>=3.2)
Requires-Dist: djangorestframework (>=3.12.2)
Project-URL: Repository, https://github.com/defineimpossible/django-rest-batteries
